README.md
setup.py
socialchoice/__init__.py
socialchoice/ballot.py
socialchoice/election.py
socialchoice/ranking_similarity.py
socialchoice/util.py
socialchoice.egg-info/PKG-INFO
socialchoice.egg-info/SOURCES.txt
socialchoice.egg-info/dependency_links.txt
socialchoice.egg-info/requires.txt
socialchoice.egg-info/top_level.txt
socialchoice/induction/__init__.py
socialchoice/induction/resolving_incompleteness.py
socialchoice/induction/resolving_intransitivity.py
socialchoice/induction/vote_induction.py
test/test_election.py
test/test_enabling_ordering_based_methods.py
test/test_incompleteness_resolver_factory.py
test/test_intransitivity_resolver_factory.py
test/test_utils.py