Metadata-Version: 2.1
Name: socialchoice
Version: 0.0.12
Summary: Social Choice Theory in Python
Home-page: https://github.com/julian-zucker/socialchoice
Author: Julian Zucker
Author-email: julian.zucker@gmail.com
License: Apache 2.0
Platform: UNKNOWN
Requires-Python: >=3
